DeepDC_PyTorch/DeepDC.py
DeepDC_PyTorch/__init__.py
DeepDC_PyTorch-0.2.dist-info/LICENSE
DeepDC_PyTorch-0.2.dist-info/METADATA
DeepDC_PyTorch-0.2.dist-info/WHEEL
DeepDC_PyTorch-0.2.dist-info/top_level.txt
DeepDC_PyTorch-0.2.dist-info/RECORD
