Metadata-Version: 2.1
Name: DeepDC-PyTorch
Version: 0.2
Summary: DeepDC: Deep Distance Correlation as a Perceptual Image Quality Evaluator
Home-page: https://github.com/h4nwei/DeepDC
Author: Hanwei ZHU
Author-email: hanwei.zhu@outlook.com
License: MIT
Keywords: pytorch,similarity,VGG,texture,structure,metric
Platform: python
Requires-Dist: torch (>=1.0)
